csv2geojson/__init__.py
csv2geojson/csv2geojson.py
csv2geojson/scripts/__init__.py
csv2geojson/scripts/cli.py
csv2geojson-0.1.0.dist-info/METADATA
csv2geojson-0.1.0.dist-info/WHEEL
csv2geojson-0.1.0.dist-info/entry_points.txt
csv2geojson-0.1.0.dist-info/licenses/LICENSE
csv2geojson-0.1.0.dist-info/RECORD
