Metadata-Version: 2.1
Name: csv2geojson
Version: 0.1.0
Summary: Convert csv to geojson
Project-URL: Homepage, https://github.com/YuChunTsao/csv2geojson
Author-email: YuChunTsao <tsao84672776@gmail.com>
License: MIT License
License-File: LICENSE
Requires-Python: >=3.7
Requires-Dist: geopandas>=0.10
Provides-Extra: dev
Requires-Dist: pytest; extra == 'dev'
Provides-Extra: test
Requires-Dist: pytest; extra == 'test'
